attribute_controller/__init__.pyi
bim_controller/__init__.pyi
cadwork/__init__.pyi
cadwork/active_point_result.py
cadwork/api_types.pyi
cadwork/attribute_display_settings.pyi
cadwork/bim_team_upload_result.pyi
cadwork/bim_team_upload_result_code.pyi
cadwork/btl_version.pyi
cadwork/camera_data.pyi
cadwork/coordinate_system_data.pyi
cadwork/dimension_base_format.pyi
cadwork/division_zone_direction.pyi
cadwork/double_shoulder_options.pyi
cadwork/dxf_export_version.pyi
cadwork/dxf_layer_format_type.pyi
cadwork/edge_list.pyi
cadwork/element_filter.pyi
cadwork/element_grouping_type.pyi
cadwork/element_map_query.pyi
cadwork/element_module_detail.pyi
cadwork/element_module_properties.pyi
cadwork/element_type.pyi
cadwork/extended_settings.pyi
cadwork/facet_list.pyi
cadwork/heel_shoulder_beam_geometry.pyi
cadwork/heel_shoulder_options.pyi
cadwork/hit_result.pyi
cadwork/hundegger_machine_type.pyi
cadwork/ifc_2x3_element_type.pyi
cadwork/ifc_element_combine_behaviour.pyi
cadwork/ifc_material_definition.pyi
cadwork/ifc_options.pyi
cadwork/ifc_options_aggregation.pyi
cadwork/ifc_options_level_of_detail.pyi
cadwork/ifc_options_project_data.pyi
cadwork/ifc_options_properties.pyi
cadwork/ifc_predefined_type.pyi
cadwork/import_3dc_options.pyi
cadwork/layer_settings.pyi
cadwork/multi_layer_cover_type.pyi
cadwork/multi_layer_subtype.pyi
cadwork/multi_layer_type.pyi
cadwork/node_symbol.pyi
cadwork/point.pyi
cadwork/point_3d.pyi
cadwork/polygon_list.pyi
cadwork/process_type.pyi
cadwork/projection_type.pyi
cadwork/rgb_color.py
cadwork/rhino_options.pyi
cadwork/shortcut_key.pyi
cadwork/shortcut_key_modifier.pyi
cadwork/shoulder_beam_geometry.pyi
cadwork/shoulder_drilling_orientation.pyi
cadwork/shoulder_options.pyi
cadwork/standard_element_type.pyi
cadwork/text_element_type.pyi
cadwork/text_object_options.pyi
cadwork/vba_catalog_item_type.pyi
cadwork/vertex_list.pyi
cadwork/weinmann_mfb_version.pyi
cadwork/window_geometry.pyi
connector_axis_controller/__init__.pyi
cwapi3d-32.443.0.dist-info/licenses/LICENSE
cwapi3d-32.443.0.dist-info/METADATA
cwapi3d-32.443.0.dist-info/WHEEL
cwapi3d-32.443.0.dist-info/top_level.txt
cwapi3d-32.443.0.dist-info/RECORD
