Metadata-Version: 2.4
Name: cwapi3d
Version: 32.443.0
Summary: Python bindings for CwAPI3D
Author-email: Cadwork <it@cadwork.ca>
License: MIT License
Project-URL: Homepage, https://github.com/cwapi3d/cwapi3dpython
Keywords: cadwork
Classifier: Development Status :: 5 - Production/Stable
Classifier: Environment :: Plugins
Classifier: Intended Audience :: Developers
Classifier: License :: OSI Approved :: MIT License
Classifier: Operating System :: Microsoft :: Windows
Classifier: Programming Language :: Python :: 3
Classifier: Programming Language :: Python :: 3.12
Classifier: Topic :: Software Development :: Libraries
Requires-Python: >=3.12
License-File: LICENSE
Dynamic: license-file
